{
  "members": [
    {
      "id": "tallcloud-ii",
      "name": "TallCloud_II",
      "state": "Indiana",
      "district": "2",
      "party": "Republican",
      "committees": [
        "Judicary Committee",
        "Select Committee on Homeland Security and Intelligence",
        "Forign Affairs Committee",
        "Armed Services and Veteran Affairs Committee",
        "Adminitration Rules and Ethics Committee"
      ],
      "votes": []
    },
    {
      "id": "noah-dremer",
      "name": "Noah Dremer",
      "state": "Colorado",
      "district": "8",
      "party": "Democrat",
      "committees": [
        "Intelligence"
      ],
      "votes": []
    }
  ]
}